lehar/VERSION
lehar/__init__.py
lehar/main.py
lehar/tests.py
lehar-0.4.dist-info/DESCRIPTION.rst
lehar-0.4.dist-info/METADATA
lehar-0.4.dist-info/RECORD
lehar-0.4.dist-info/WHEEL
lehar-0.4.dist-info/entry_points.txt
lehar-0.4.dist-info/metadata.json
lehar-0.4.dist-info/top_level.txt
