Metadata-Version: 2.0
Name: lehar
Version: 0.4
Summary: UNKNOWN
Home-page: https://github.com/darxtrix/lehar
Author: Ankush Sharma
Author-email: darxtrix@gmail.com
License: MIT
Keywords: terminal sparklines spark unicode lehar shell
Platform: UNKNOWN
Classifier: Development Status :: 5 - Production/Stable
Classifier: Intended Audience :: Developers
Classifier: Topic :: Software Development :: Build Tools
Classifier: License :: OSI Approved :: MIT License
Classifier: Programming Language :: Python :: 2
Classifier: Programming Language :: Python :: 2.7
Classifier: Programming Language :: Python :: 3
Classifier: Programming Language :: Python :: 3.3
Classifier: Programming Language :: Python :: 3.4
Classifier: Programming Language :: Python :: 3.5
Provides-Extra: dev
Provides-Extra: test
Requires-Dist: codeclimate-test-reporter; extra == 'test'
Requires-Dist: coverage; extra == 'test'
